change_wheel_version.py
change_wheel_version-0.6.0.dist-info/entry_points.txt
change_wheel_version-0.6.0.dist-info/LICENSE
change_wheel_version-0.6.0.dist-info/WHEEL
change_wheel_version-0.6.0.dist-info/METADATA
change_wheel_version-0.6.0.dist-info/RECORD
