Metadata-Version: 2.1
Name: change_wheel_version
Version: 0.6.0
Summary: Change the version of a wheel file
Keywords: wheel,version,packaging
Requires-Python: >=3.9
Requires-Dist: wheel
Requires-Dist: installer
Requires-Dist: packaging
Project-URL: changelog, https://github.com/hauntsaninja/change_wheel_version/blob/master/CHANGELOG.md
Project-URL: repository, https://github.com/hauntsaninja/change_wheel_version
